setup.py
amino/__coconut__.py
amino/__init__.py
amino/algebra.py
amino/async.py
amino/bi_rose_tree.py
amino/boolean.py
amino/dat.py
amino/dispatch.py
amino/do.py
amino/eff.py
amino/either.py
amino/env_vars.py
amino/eval.py
amino/func.py
amino/future.py
amino/id.py
amino/io.py
amino/lazy.py
amino/lazy_list.py
amino/list.py
amino/logging.py
amino/map.py
amino/maybe.py
amino/mod.py
amino/options.py
amino/regex.py
amino/state.py
amino/transformer.py
amino/tree.py
amino/typecheck.py
amino.egg-info/PKG-INFO
amino.egg-info/SOURCES.txt
amino.egg-info/dependency_links.txt
amino.egg-info/requires.txt
amino.egg-info/top_level.txt
amino/anon/__init__.py
amino/anon/boot.py
amino/anon/debug.py
amino/anon/error.py
amino/anon/prod/__init__.py
amino/anon/prod/attr.py
amino/anon/prod/complex.py
amino/anon/prod/method.py
amino/coco/__init__.py
amino/instances/__init__.py
amino/instances/either.py
amino/instances/io.py
amino/instances/lazy_list.py
amino/instances/list.py
amino/instances/map.py
amino/instances/maybe.py
amino/instances/std/__init__.py
amino/instances/std/datetime.py
amino/json/__coconut__.py
amino/json/__init__.py
amino/json/data.py
amino/json/decoder.py
amino/json/decoders.py
amino/json/encoder.py
amino/json/encoders.py
amino/json/parse.py
amino/lens/__init__.py
amino/lens/tree.py
amino/tc/__init__.py
amino/tc/applicative.py
amino/tc/apply.py
amino/tc/base.py
amino/tc/flat_map.py
amino/tc/foldable.py
amino/tc/functor.py
amino/tc/monad.py
amino/tc/monoid.py
amino/tc/monoidal.py
amino/tc/optional.py
amino/tc/show.py
amino/tc/tap.py
amino/tc/traverse.py
amino/tc/zip.py
amino/test/__init__.py
amino/test/path.py
amino/test/spec.py
amino/test/spec_spec.py
amino/test/sure.py
amino/test/sure_ext.py
amino/util/__init__.py
amino/util/ast.py
amino/util/coconut_mypy.py
amino/util/exception.py
amino/util/fun.py
amino/util/mod.py
amino/util/numeric.py
amino/util/random.py
amino/util/string.py
amino/util/tpe.py