Metadata-Version: 1.0
Name: amino
Version: 12.5.4
Summary: functional data structures and type classes
Home-page: https://github.com/tek/amino
Author: Torsten Schmits
Author-email: torstenschmits@gmail.com
License: MIT
Platform: UNKNOWN
